README.md
setup.py
Pythark.egg-info/PKG-INFO
Pythark.egg-info/SOURCES.txt
Pythark.egg-info/dependency_links.txt
Pythark.egg-info/not-zip-safe
Pythark.egg-info/requires.txt
Pythark.egg-info/top_level.txt
pythark/__init__.py
pythark/account.py
pythark/api.py
pythark/block.py
pythark/delegate.py
pythark/loader.py
pythark/multisignature.py
pythark/peer.py
pythark/signature.py
pythark/transaction.py
pythark/transport.py
tests/__init__.py
tests/test_account.py
tests/test_block.py
tests/test_delegate.py
tests/test_loader.py
tests/test_multisignature.py
tests/test_peer.py
tests/test_signature.py
tests/test_transaction.py
tests/test_transport.py