Metadata-Version: 1.2
Name: Pythark
Version: 0.1.6
Summary: Ark API Wrapper
Home-page: https://github.com/Highjhacker/pythark
Author: Highjhacker
Author-email: jolanbeer@gmail.com
License: MIT
Keywords: Ark python wrapper api
Platform: UNKNOWN
Classifier: Development Status :: 4 - Beta
Classifier: Intended Audience :: Developers
Classifier: Topic :: Software Development :: Build Tools
Classifier: License :: OSI Approved :: MIT License
Requires-Python: >=3
